MANIFEST.in
readme_pypi.rst
setup.py
pcs_api/__init__.py
pcs_api/_version.py
pcs_api/bytes_io.py
pcs_api/cexceptions.py
pcs_api/models.py
pcs_api/storage.py
pcs_api/utils.py
pcs_api.egg-info/PKG-INFO
pcs_api.egg-info/SOURCES.txt
pcs_api.egg-info/dependency_links.txt
pcs_api.egg-info/requires.txt
pcs_api.egg-info/top_level.txt
pcs_api/credentials/__init__.py
pcs_api/credentials/app_info.py
pcs_api/credentials/app_info_file_repo.py
pcs_api/credentials/user_credentials.py
pcs_api/credentials/user_creds_file_repo.py
pcs_api/oauth/__init__.py
pcs_api/oauth/oauth2_bootstrap.py
pcs_api/oauth/oauth2_params.py
pcs_api/oauth/session_managers.py
pcs_api/providers/__init__.py
pcs_api/providers/cloudme.py
pcs_api/providers/dropbox.py
pcs_api/providers/googledrive.py
pcs_api/providers/hubic.py
pcs_api/providers/kanbox.py
pcs_api/providers/rapidshare.py
pcs_api/providers/swift.py