Metadata-Version: 1.1
Name: pcs-api
Version: 1.0.1
Summary: A library that gives a uniform API to several personal cloud files storage providers (Dropbox, Google Drive...)
Home-page: https://github.com/netheosgithub/pcs_api
Author: Netheos
Author-email: contact@netheos.net
License: Apache Software License V2.0
Download-URL: https://github.com/netheosgithub/pcs_api/releases
Platform: any
Classifier: Programming Language :: Python
Classifier: Development Status :: 5 - Production/Stable
Classifier: Natural Language :: English
Classifier: Intended Audience :: Developers
Classifier: License :: OSI Approved :: Apache Software License
Classifier: Operating System :: OS Independent
Classifier: Programming Language :: Python :: 2.7
Classifier: Topic :: Internet :: WWW/HTTP
Classifier: Topic :: Communications :: File Sharing
Classifier: Topic :: Software Development :: Libraries :: Python Modules
